trendlines/__about__.py
trendlines/__init__.py
trendlines/_logging.py
trendlines/app_factory.py
trendlines/celery_app.py
trendlines/celery_factory.py
trendlines/db.py
trendlines/default_config.py
trendlines/error_responses.py
trendlines/orm.py
trendlines/routes.py
trendlines/utils.py
trendlines-0.5.0.dist-info/LICENSE
trendlines-0.5.0.dist-info/METADATA
trendlines-0.5.0.dist-info/WHEEL
trendlines-0.5.0.dist-info/top_level.txt
trendlines-0.5.0.dist-info/RECORD
