Metadata-Version: 2.1
Name: trendlines
Version: 0.5.0
Summary: Lightweight time-series recording.
Home-page: https://github.com/dougthor42/trendlines
Author: Douglas Thor
Author-email: doug.thor@gmail.com
License: UNKNOWN
Platform: UNKNOWN
Requires-Python: >=3.5
Requires-Dist: flask (>=1.0)
Requires-Dist: peewee (>=3.8)
